{"nodes": [{"id": "c_users_migue_desktop_liz_cabriales_app_api_admin_courses_route_ts", "label": "route.ts", "file_type": "code", "source_file": "C:\\Users\\migue\\Desktop\\liz-cabriales\\app\\api\\admin\\courses\\route.ts", "source_location": "L1"}, {"id": "courses_route_errorresponse", "label": "errorResponse()", "file_type": "code", "source_file": "C:\\Users\\migue\\Desktop\\liz-cabriales\\app\\api\\admin\\courses\\route.ts", "source_location": "L13"}, {"id": "courses_route_assertadmin", "label": "assertAdmin()", "file_type": "code", "source_file": "C:\\Users\\migue\\Desktop\\liz-cabriales\\app\\api\\admin\\courses\\route.ts", "source_location": "L24"}, {"id": "courses_route_get", "label": "GET()", "file_type": "code", "source_file": "C:\\Users\\migue\\Desktop\\liz-cabriales\\app\\api\\admin\\courses\\route.ts", "source_location": "L33"}, {"id": "courses_route_post", "label": "POST()", "file_type": "code", "source_file": "C:\\Users\\migue\\Desktop\\liz-cabriales\\app\\api\\admin\\courses\\route.ts", "source_location": "L65"}], "edges": [{"source": "c_users_migue_desktop_liz_cabriales_app_api_admin_courses_route_ts", "target": "server", "relation": "imports_from", "context": "import", "confidence": "EXTRACTED", "source_file": "C:\\Users\\migue\\Desktop\\liz-cabriales\\app\\api\\admin\\courses\\route.ts", "source_location": "L1", "weight": 1.0}, {"source": "c_users_migue_desktop_liz_cabriales_app_api_admin_courses_route_ts", "target": "c_users_migue_desktop_liz_cabriales_lib_supabase_server", "relation": "imports_from", "context": "import", "confidence": "EXTRACTED", "source_file": "C:\\Users\\migue\\Desktop\\liz-cabriales\\app\\api\\admin\\courses\\route.ts", "source_location": "L3", "weight": 1.0}, {"source": "c_users_migue_desktop_liz_cabriales_app_api_admin_courses_route_ts", "target": "supabase_server_createclient", "relation": "imports", "context": "import", "confidence": "EXTRACTED", "source_file": "C:\\Users\\migue\\Desktop\\liz-cabriales\\app\\api\\admin\\courses\\route.ts", "source_location": "L3", "weight": 1.0}, {"source": "c_users_migue_desktop_liz_cabriales_app_api_admin_courses_route_ts", "target": "c_users_migue_desktop_liz_cabriales_lib_supabase_admin", "relation": "imports_from", "context": "import", "confidence": "EXTRACTED", "source_file": "C:\\Users\\migue\\Desktop\\liz-cabriales\\app\\api\\admin\\courses\\route.ts", "source_location": "L4", "weight": 1.0}, {"source": "c_users_migue_desktop_liz_cabriales_app_api_admin_courses_route_ts", "target": "supabase_admin_requireadmin", "relation": "imports", "context": "import", "confidence": "EXTRACTED", "source_file": "C:\\Users\\migue\\Desktop\\liz-cabriales\\app\\api\\admin\\courses\\route.ts", "source_location": "L4", "weight": 1.0}, {"source": "c_users_migue_desktop_liz_cabriales_app_api_admin_courses_route_ts", "target": "c_users_migue_desktop_liz_cabriales_lib_supabase_courses", "relation": "imports_from", "context": "import", "confidence": "EXTRACTED", "source_file": "C:\\Users\\migue\\Desktop\\liz-cabriales\\app\\api\\admin\\courses\\route.ts", "source_location": "L5", "weight": 1.0}, {"source": "c_users_migue_desktop_liz_cabriales_app_api_admin_courses_route_ts", "target": "supabase_courses_createcourse", "relation": "imports", "context": "import", "confidence": "EXTRACTED", "source_file": "C:\\Users\\migue\\Desktop\\liz-cabriales\\app\\api\\admin\\courses\\route.ts", "source_location": "L5", "weight": 1.0}, {"source": "c_users_migue_desktop_liz_cabriales_app_api_admin_courses_route_ts", "target": "supabase_courses_getadmincourses", "relation": "imports", "context": "import", "confidence": "EXTRACTED", "source_file": "C:\\Users\\migue\\Desktop\\liz-cabriales\\app\\api\\admin\\courses\\route.ts", "source_location": "L5", "weight": 1.0}, {"source": "c_users_migue_desktop_liz_cabriales_app_api_admin_courses_route_ts", "target": "c_users_migue_desktop_liz_cabriales_lib_validations_courses", "relation": "imports_from", "context": "import", "confidence": "EXTRACTED", "source_file": "C:\\Users\\migue\\Desktop\\liz-cabriales\\app\\api\\admin\\courses\\route.ts", "source_location": "L6", "weight": 1.0}, {"source": "c_users_migue_desktop_liz_cabriales_app_api_admin_courses_route_ts", "target": "validations_courses_createcourseschema", "relation": "imports", "context": "import", "confidence": "EXTRACTED", "source_file": "C:\\Users\\migue\\Desktop\\liz-cabriales\\app\\api\\admin\\courses\\route.ts", "source_location": "L6", "weight": 1.0}, {"source": "c_users_migue_desktop_liz_cabriales_app_api_admin_courses_route_ts", "target": "courses_route_errorresponse", "relation": "contains", "confidence": "EXTRACTED", "source_file": "C:\\Users\\migue\\Desktop\\liz-cabriales\\app\\api\\admin\\courses\\route.ts", "source_location": "L13", "weight": 1.0}, {"source": "c_users_migue_desktop_liz_cabriales_app_api_admin_courses_route_ts", "target": "courses_route_assertadmin", "relation": "contains", "confidence": "EXTRACTED", "source_file": "C:\\Users\\migue\\Desktop\\liz-cabriales\\app\\api\\admin\\courses\\route.ts", "source_location": "L24", "weight": 1.0}, {"source": "c_users_migue_desktop_liz_cabriales_app_api_admin_courses_route_ts", "target": "courses_route_get", "relation": "contains", "confidence": "EXTRACTED", "source_file": "C:\\Users\\migue\\Desktop\\liz-cabriales\\app\\api\\admin\\courses\\route.ts", "source_location": "L33", "weight": 1.0}, {"source": "c_users_migue_desktop_liz_cabriales_app_api_admin_courses_route_ts", "target": "courses_route_post", "relation": "contains", "confidence": "EXTRACTED", "source_file": "C:\\Users\\migue\\Desktop\\liz-cabriales\\app\\api\\admin\\courses\\route.ts", "source_location": "L65", "weight": 1.0}, {"source": "courses_route_get", "target": "courses_route_assertadmin", "relation": "calls", "context": "call", "confidence": "EXTRACTED", "source_file": "C:\\Users\\migue\\Desktop\\liz-cabriales\\app\\api\\admin\\courses\\route.ts", "source_location": "L35", "weight": 1.0}, {"source": "courses_route_get", "target": "courses_route_errorresponse", "relation": "calls", "context": "call", "confidence": "EXTRACTED", "source_file": "C:\\Users\\migue\\Desktop\\liz-cabriales\\app\\api\\admin\\courses\\route.ts", "source_location": "L43", "weight": 1.0}, {"source": "courses_route_post", "target": "courses_route_assertadmin", "relation": "calls", "context": "call", "confidence": "EXTRACTED", "source_file": "C:\\Users\\migue\\Desktop\\liz-cabriales\\app\\api\\admin\\courses\\route.ts", "source_location": "L67", "weight": 1.0}, {"source": "courses_route_post", "target": "courses_route_errorresponse", "relation": "calls", "context": "call", "confidence": "EXTRACTED", "source_file": "C:\\Users\\migue\\Desktop\\liz-cabriales\\app\\api\\admin\\courses\\route.ts", "source_location": "L75", "weight": 1.0}], "raw_calls": [{"caller_nid": "courses_route_errorresponse", "callee": "json", "is_member_call": true, "source_file": "C:\\Users\\migue\\Desktop\\liz-cabriales\\app\\api\\admin\\courses\\route.ts", "source_location": "L18"}, {"caller_nid": "courses_route_assertadmin", "callee": "createClient", "is_member_call": false, "source_file": "C:\\Users\\migue\\Desktop\\liz-cabriales\\app\\api\\admin\\courses\\route.ts", "source_location": "L25"}, {"caller_nid": "courses_route_assertadmin", "callee": "getUser", "is_member_call": true, "source_file": "C:\\Users\\migue\\Desktop\\liz-cabriales\\app\\api\\admin\\courses\\route.ts", "source_location": "L28"}, {"caller_nid": "courses_route_assertadmin", "callee": "requireAdmin", "is_member_call": false, "source_file": "C:\\Users\\migue\\Desktop\\liz-cabriales\\app\\api\\admin\\courses\\route.ts", "source_location": "L29"}, {"caller_nid": "courses_route_get", "callee": "getAdminCourses", "is_member_call": false, "source_file": "C:\\Users\\migue\\Desktop\\liz-cabriales\\app\\api\\admin\\courses\\route.ts", "source_location": "L50"}, {"caller_nid": "courses_route_get", "callee": "json", "is_member_call": true, "source_file": "C:\\Users\\migue\\Desktop\\liz-cabriales\\app\\api\\admin\\courses\\route.ts", "source_location": "L55"}, {"caller_nid": "courses_route_get", "callee": "error", "is_member_call": true, "source_file": "C:\\Users\\migue\\Desktop\\liz-cabriales\\app\\api\\admin\\courses\\route.ts", "source_location": "L60"}, {"caller_nid": "courses_route_post", "callee": "json", "is_member_call": true, "source_file": "C:\\Users\\migue\\Desktop\\liz-cabriales\\app\\api\\admin\\courses\\route.ts", "source_location": "L84"}, {"caller_nid": "courses_route_post", "callee": "safeParse", "is_member_call": true, "source_file": "C:\\Users\\migue\\Desktop\\liz-cabriales\\app\\api\\admin\\courses\\route.ts", "source_location": "L89"}, {"caller_nid": "courses_route_post", "callee": "createCourse", "is_member_call": false, "source_file": "C:\\Users\\migue\\Desktop\\liz-cabriales\\app\\api\\admin\\courses\\route.ts", "source_location": "L98"}, {"caller_nid": "courses_route_post", "callee": "json", "is_member_call": true, "source_file": "C:\\Users\\migue\\Desktop\\liz-cabriales\\app\\api\\admin\\courses\\route.ts", "source_location": "L103"}, {"caller_nid": "courses_route_post", "callee": "error", "is_member_call": true, "source_file": "C:\\Users\\migue\\Desktop\\liz-cabriales\\app\\api\\admin\\courses\\route.ts", "source_location": "L108"}]}